{
  "mainScript": "main",
  "engines": [
    {
      "name": "node",
      "exe": "node",
      "ext": "js"
    }, {
      "name": "electron",
      "exe": "C:/Users/Thomas/AppData/Roaming/npm/node_modules/electron/dist/electron.exe",
      "script": "electron.js",
      "options": {
        "skipFirst": true,
        "killOnSigint": false
      }
    }, {
      "name": "python",
      "exe": "C:/Users/Thomas/AppData/Local/Programs/Python/Python37/python.exe",
      "ext": "py"
    }
  ]
}